google/cloud/retail/__init__.py
google/cloud/retail/gapic_version.py
google/cloud/retail/py.typed
google/cloud/retail_v2/__init__.py
google/cloud/retail_v2/gapic_metadata.json
google/cloud/retail_v2/gapic_version.py
google/cloud/retail_v2/py.typed
google/cloud/retail_v2/services/__init__.py
google/cloud/retail_v2/services/analytics_service/__init__.py
google/cloud/retail_v2/services/analytics_service/async_client.py
google/cloud/retail_v2/services/analytics_service/client.py
google/cloud/retail_v2/services/analytics_service/transports/__init__.py
google/cloud/retail_v2/services/analytics_service/transports/base.py
google/cloud/retail_v2/services/analytics_service/transports/grpc.py
google/cloud/retail_v2/services/analytics_service/transports/grpc_asyncio.py
google/cloud/retail_v2/services/analytics_service/transports/rest.py
google/cloud/retail_v2/services/analytics_service/transports/rest_base.py
google/cloud/retail_v2/services/catalog_service/__init__.py
google/cloud/retail_v2/services/catalog_service/async_client.py
google/cloud/retail_v2/services/catalog_service/client.py
google/cloud/retail_v2/services/catalog_service/pagers.py
google/cloud/retail_v2/services/catalog_service/transports/__init__.py
google/cloud/retail_v2/services/catalog_service/transports/base.py
google/cloud/retail_v2/services/catalog_service/transports/grpc.py
google/cloud/retail_v2/services/catalog_service/transports/grpc_asyncio.py
google/cloud/retail_v2/services/catalog_service/transports/rest.py
google/cloud/retail_v2/services/catalog_service/transports/rest_base.py
google/cloud/retail_v2/services/completion_service/__init__.py
google/cloud/retail_v2/services/completion_service/async_client.py
google/cloud/retail_v2/services/completion_service/client.py
google/cloud/retail_v2/services/completion_service/transports/__init__.py
google/cloud/retail_v2/services/completion_service/transports/base.py
google/cloud/retail_v2/services/completion_service/transports/grpc.py
google_cloud_retail-2.9.0.dist-info/licenses/LICENSE
google_cloud_retail-2.9.0.dist-info/METADATA
google_cloud_retail-2.9.0.dist-info/WHEEL
google_cloud_retail-2.9.0.dist-info/top_level.txt
google_cloud_retail-2.9.0.dist-info/RECORD
